LICENSE.txt
MANIFEST.in
Pipfile
Pipfile.lock
README.md
setup.py
error_explainer/__init__.py
error_explainer/check.py
error_explainer/check_runner.py
error_explainer/checks.py
error_explainer/colon_statements.py
error_explainer/messages.py
error_explainer/utils.py
error_explainer.egg-info/PKG-INFO
error_explainer.egg-info/SOURCES.txt
error_explainer.egg-info/dependency_links.txt
error_explainer.egg-info/top_level.txt
test/__init__.py
test/assignment_test.py
test/brackets_test.py
test/colon_tests.py
test/def_test.py
test/indentation_test.py
test/quotes_test.py
test/sanity_test.py
test/test_utils.py
test/assignment_samples/assignment_to_constant_error_1.py
test/assignment_samples/assignment_to_constant_error_2.py
test/assignment_samples/assignment_to_constant_error_3.py
test/assignment_samples/assignment_to_expr_error.py
test/assignment_samples/assignment_to_function_error.py
test/assignment_samples/assignment_to_keyword_error.py
test/assignment_samples/coma_instead_of_period_error.py
test/assignment_samples/comparison_assignment_correct.py
test/assignment_samples/multiple_assignment_func_var_error.py
test/assignment_samples/tuple_assign_correct.py
test/brackets_samples/mismatched_bracket_error.py
test/brackets_samples/mismatched_bracket_multiline_error.py
test/brackets_samples/missing_bracket_after_error.py
test/brackets_samples/missing_brackets_print_error.py
test/brackets_samples/missing_square_bracket_after2_error.py
test/brackets_samples/missing_square_bracket_after_error.py
test/brackets_samples/raise_syntax_error15.py
test/brackets_samples/raise_syntax_error17.py
test/colon_samples/missing_colon_after_if_error.py
test/colon_samples/missing_colon_after_while_error.py
test/def_samples/assign_to_def_error.py
test/def_samples/keyword_as_arg_name_error.py
test/def_samples/keyword_as_function_name_error.py
test/def_samples/no_name_or_args_def_error.py
test/def_samples/no_name_or_args_def_error2.py
test/def_samples/no_name_or_args_def_error3.py
test/indentation_samples/false_positive_else.py
test/indentation_samples/higher_level_of_indent_with_no_start_error.py
test/indentation_samples/no_matching_indent_level_error.py
