Metadata-Version: 2.1
Name: error-explainer
Version: 0.14
Summary: Custom messages for errors
Home-page: https://github.com/K44rel/error-explainer
Author: Kaarel Loide
Author-email: kaarel.loide@gmail.com
License: UNKNOWN
Platform: UNKNOWN
Classifier: Development Status :: 3 - Alpha
Classifier: Intended Audience :: Developers
Classifier: Topic :: Software Development
Classifier: License :: OSI Approved :: MIT License
Classifier: Programming Language :: Python :: 3.6
Classifier: Programming Language :: Python :: 3.7
